blaseball_reference/__init__.py
blaseball_reference/api.py
blaseball_reference/models/__init__.py
blaseball_reference/models/base_runner.py
blaseball_reference/models/game_event.py
blaseball_reference/models/player_event.py
blaseball_reference-2.1.1.dist-info/LICENSE
blaseball_reference-2.1.1.dist-info/METADATA
blaseball_reference-2.1.1.dist-info/WHEEL
blaseball_reference-2.1.1.dist-info/top_level.txt
blaseball_reference-2.1.1.dist-info/RECORD
