Metadata-Version: 2.1
Name: blaseball-reference
Version: 2.1.1
Summary: Python wrapper around blaseball-reference API
Home-page: https://github.com/jmaliksi/blaseball-reference-py
Author: Joe Maliksi
Author-email: joe.maliksi@gmail.com
License: UNKNOWN
Platform: UNKNOWN
